langgraph_checkpoint_postgres_pg8000/__init__.py
langgraph_checkpoint_postgres_pg8000/pg8000_saver.py
langgraph_checkpoint_postgres_pg8000/py.typed
langgraph_checkpoint_postgres_pg8000-1.0.1.dist-info/METADATA
langgraph_checkpoint_postgres_pg8000-1.0.1.dist-info/WHEEL
langgraph_checkpoint_postgres_pg8000-1.0.1.dist-info/licenses/LICENSE
langgraph_checkpoint_postgres_pg8000-1.0.1.dist-info/RECORD
