Metadata-Version: 2.4
Name: langgraph-checkpoint-postgres-pg8000
Version: 1.0.1
Summary: LangGraph checkpointer implementation using pg8000 for PostgreSQL. Compatible with Google Cloud SQL Connector.
Project-URL: Homepage, https://github.com/CodifyIQ/langgraph-checkpoint-postgres-pg8000
Project-URL: Repository, https://github.com/CodifyIQ/langgraph-checkpoint-postgres-pg8000
Project-URL: Issues, https://github.com/CodifyIQ/langgraph-checkpoint-postgres-pg8000/issues
Author-email: Eric Konieczny <eric.konieczny@codifyiq.com>
License: MIT
License-File: LICENSE
Keywords: checkpoint,google-cloud-sql,langgraph,pg8000,postgres,sqlalchemy
Classifier: Development Status :: 4 - Beta
Classifier: Intended Audience :: Developers
Classifier: License :: OSI Approved :: MIT License
Classifier: Operating System :: OS Independent
Classifier: Programming Language :: Python :: 3
Classifier: Programming Language :: Python :: 3.12
Classifier: Programming Language :: Python :: 3.13
Requires-Python: >=3.12
Requires-Dist: langgraph-checkpoint>=2.0.0
Requires-Dist: pg8000>=1.30.0
Requires-Dist: sqlalchemy>=2.0.0
